{"cameraMode":{"drawMode":0,"name":"Shaded","section":"Shading Mode"},"sceneLighting":true,"audioPlay":false,"sceneViewState":{"showFog":true,"showMaterialUpdate":false,"showSkybox":true,"showFlares":true,"showImageEffects":true,"showParticleSystems":true},"in2DMode":false,"pivot":{"x":1.2076534032821656,"y":0.7009422779083252,"z":-1.8036376237869263},"rotation":{"x":-0.19237355887889863,"y":0.04767075926065445,"z":-0.00934707559645176,"w":-0.9801285266876221},"size":1.7540373802185059,"orthographic":false}